pyfortified_cache/__init__.py
pyfortified_cache/abstract_cache.py
pyfortified_cache/cache_client.py
pyfortified_cache/cache_factory.py
pyfortified_cache/cache_types.py
pyfortified_cache/constants.py
pyfortified_cache/errors.py
pyfortified_cache/local_cache.py
pyfortified_cache/memcached_cache.py
pyfortified_cache/utils.py
pyfortified_cache-0.1.2.dist-info/METADATA
pyfortified_cache-0.1.2.dist-info/RECORD
pyfortified_cache-0.1.2.dist-info/WHEEL
pyfortified_cache-0.1.2.dist-info/top_level.txt
